{
  "version": "7",
  "dialect": "postgresql",
  "entries": [
    {
      "idx": 0,
      "version": "7",
      "when": 1778001691890,
      "tag": "0000_sloppy_blackheart",
      "breakpoints": true
    },
    {
      "idx": 1,
      "version": "7",
      "when": 1778001700000,
      "tag": "0001_search_extensions",
      "breakpoints": true
    },
    {
      "idx": 2,
      "version": "7",
      "when": 1778001701000,
      "tag": "0002_nullable_nursing_visit_base_price",
      "breakpoints": true
    }
  ]
}
